NitrotypePy/__init__.py
NitrotypePy/api/__init__.py
NitrotypePy/api/access.py
NitrotypePy/api/apiv2/__init__.py
NitrotypePy/api/apiv2/api.py
NitrotypePy/api/apiv2/endpoints/__init__.py
NitrotypePy/api/apiv2/endpoints/leaderboard.py
NitrotypePy/api/apiv2/endpoints/news.py
NitrotypePy/api/apiv2/endpoints/teams.py
NitrotypePy/api/info/__init__.py
NitrotypePy/api/info/user.py
NitrotypePy/api/info/bootstrap/__init__.py
NitrotypePy/api/info/bootstrap/bootstrap.py
NitrotypePy/api/info/bootstrap/items/__init__.py
NitrotypePy/api/info/bootstrap/items/car.py
NitrotypePy/api/info/bootstrap/items/loot.py
NitrotypePy/api/info/bootstrap/misc/__init__.py
NitrotypePy/api/info/bootstrap/misc/challenges.py
NitrotypePy/api/info/bootstrap/misc/top.py
NitrotypePy/objects/api/apiv2/endpoints/__init__.py
NitrotypePy/objects/api/apiv2/endpoints/leaderboard.py
NitrotypePy/objects/api/apiv2/endpoints/news.py
NitrotypePy/objects/api/info/__init__.py
NitrotypePy/objects/api/info/user.py
NitrotypePy/objects/api/info/bootstrap/basic_object.py
NitrotypePy/objects/api/info/bootstrap/item/__init__.py
NitrotypePy/objects/api/info/bootstrap/item/car.py
NitrotypePy/objects/api/info/bootstrap/item/loot.py
NitrotypePy/objects/api/info/bootstrap/misc/__init__.py
NitrotypePy/objects/api/info/bootstrap/misc/challenges.py
NitrotypePy-0.0.6.dist-info/LICENSE
NitrotypePy-0.0.6.dist-info/METADATA
NitrotypePy-0.0.6.dist-info/WHEEL
NitrotypePy-0.0.6.dist-info/top_level.txt
NitrotypePy-0.0.6.dist-info/RECORD
