Metadata-Version: 2.1
Name: NitrotypePy
Version: 0.0.6
Summary: A way to access nitrotype's unofficial api.
Home-page: https://www.github.com/RangerEmerald/NitrotypePy
Author: The Moon That Rises
License: MIT
Platform: UNKNOWN
License-File: LICENSE
Requires-Dist: cloudscraper (>=1.2.58)
